README.rst
setup.py
chores/__init__.py
chores/core.py
chores/counterstuf.py
chores/setspec.py
chores/stages.py
chores/version.py
chores.egg-info/PKG-INFO
chores.egg-info/SOURCES.txt
chores.egg-info/dependency_links.txt
chores.egg-info/not-zip-safe
chores.egg-info/requires.txt
chores.egg-info/top_level.txt
test/test.py
test/test_counterstuf.py
test/test_setspec.py
test/test_stages.py